AST_data_eng/__init__.py
AST_data_eng/az_proc.py
AST_data_eng/compare.py
AST_data_eng/correct_labels.py
AST_data_eng/data_characteristics.py
AST_data_eng/form_calcs.py
AST_data_eng/geolocating.py
AST_data_eng/merge.py
AST_data_eng/misc.py
AST_data_eng/processing_organizing_images_tiles.py
AST_data_eng-0.0.5.dist-info/LICENSE
AST_data_eng-0.0.5.dist-info/METADATA
AST_data_eng-0.0.5.dist-info/WHEEL
AST_data_eng-0.0.5.dist-info/top_level.txt
AST_data_eng-0.0.5.dist-info/RECORD
