Metadata-Version: 2.1
Name: AST-data-eng
Version: 0.0.5
Summary: Data engineering for large scale geospatial datasets
Home-page: http://github.com/celinerobi/
Author: Celine Robinson
Author-email: <cscrobi@gmail.com>
Keywords: python,first package
Classifier: Development Status :: 3 - Alpha
Classifier: Programming Language :: Python :: 3
Classifier: Operating System :: MacOS :: MacOS X
Classifier: Operating System :: Microsoft :: Windows
Requires-Python: >=3.8
License-File: LICENSE
Requires-Dist: numpy (>=1.21.2)
Requires-Dist: opencv-python (>=4.5.3.56)
Requires-Dist: pandas (>=1.3.3)
Requires-Dist: matplotlib (>=3.5.1)
Requires-Dist: GDAL (>=3.4.1)
Requires-Dist: Fiona (>=1.8.20)
Requires-Dist: geopandas (>=0.10.2)
Requires-Dist: geopy (>=2.2.0)
Requires-Dist: rasterio (>=1.2.10)
Requires-Dist: rioxarray (>=0.10.1)
Requires-Dist: Shapely (>=1.8.1)
Requires-Dist: pyproj (>=3.3.0)
Requires-Dist: Pillow (>=8.3.1)
Requires-Dist: progressbar2 (>=3.54.0)
Requires-Dist: Rtree (>=0.9.7)
Requires-Dist: scikit-image (>=0.16.2)
Requires-Dist: scikit-learn (>=1.0.2)
Requires-Dist: lxml (>=4.6.4)
Requires-Dist: tqdm (>=4.62.2)
